ailiga/APNPucky/DQNFighter/v0/DQNFighter_v0.py
ailiga/APNPucky/DQNFighter/v0/knights_archers_zombies_v10/DQNFighter_v0.pth
ailiga/APNPucky/DQNFighter/v0/knights_archers_zombies_v10/DQNFighter_v1.pth
ailiga/APNPucky/DQNFighter/v0/knights_archers_zombies_v10/DQNFighter_v2.pth
ailiga/APNPucky/DQNFighter/v0/leduc_holdem_v4/DQNFighter_v0.pth
ailiga/APNPucky/DQNFighter/v0/leduc_holdem_v4/DQNFighter_v1.pth
ailiga/APNPucky/DQNFighter/v0/leduc_holdem_v4/DQNFighter_v2.pth
ailiga/APNPucky/DQNFighter/v0/simple_spread_v2/APN-Pucky/PPOFighter_v0.pth
ailiga/APNPucky/DQNFighter/v0/simple_spread_v2/DQNFighter_v0.pth
ailiga/APNPucky/DQNFighter/v0/simple_spread_v2/DQNFighter_v1.pth
ailiga/APNPucky/DQNFighter/v0/simple_spread_v2/DQNFighter_v2.pth
ailiga/APNPucky/DQNFighter/v0/tictactoe_v3/APN-Pucky/PPOFighter_v0.pth
ailiga/APNPucky/DQNFighter/v0/tictactoe_v3/DQNFighter_v0.pth
ailiga/APNPucky/DQNFighter/v0/tictactoe_v3/DQNFighter_v1.pth
ailiga/APNPucky/DQNFighter/v0/tictactoe_v3/DQNFighter_v2.pth
ailiga/APNPucky/DQNFighter/v1/DQNFighter_v1.py
ailiga/APNPucky/DQNFighter/v1/knights_archers_zombies_v10/DQNFighter_v0.pth
ailiga/APNPucky/DQNFighter/v1/knights_archers_zombies_v10/DQNFighter_v1.pth
ailiga/APNPucky/DQNFighter/v1/knights_archers_zombies_v10/DQNFighter_v2.pth
ailiga/APNPucky/DQNFighter/v1/leduc_holdem_v4/DQNFighter_v0.pth
ailiga/APNPucky/DQNFighter/v1/leduc_holdem_v4/DQNFighter_v1.pth
ailiga/APNPucky/DQNFighter/v1/leduc_holdem_v4/DQNFighter_v2.pth
ailiga/APNPucky/DQNFighter/v1/simple_spread_v2/APN-Pucky/PPOFighter_v0.pth
ailiga/APNPucky/DQNFighter/v1/simple_spread_v2/DQNFighter_v0.pth
ailiga/APNPucky/DQNFighter/v1/simple_spread_v2/DQNFighter_v1.pth
ailiga/APNPucky/DQNFighter/v1/simple_spread_v2/DQNFighter_v2.pth
ailiga/APNPucky/DQNFighter/v1/tictactoe_v3/APN-Pucky/PPOFighter_v0.pth
ailiga/APNPucky/DQNFighter/v1/tictactoe_v3/DQNFighter_v0.pth
ailiga/APNPucky/DQNFighter/v1/tictactoe_v3/DQNFighter_v1.pth
ailiga/APNPucky/DQNFighter/v1/tictactoe_v3/DQNFighter_v2.pth
ailiga-2023.1.dist-info/entry_points.txt
ailiga-2023.1.dist-info/METADATA
ailiga-2023.1.dist-info/LICENSE
ailiga-2023.1.dist-info/WHEEL
ailiga-2023.1.dist-info/RECORD
