Metadata-Version: 2.1
Name: ailiga
Version: 2023.1
Summary: 
Author: Alexander Puck Neuwirth
Author-email: alexander@neuwirth-informatik.de
Requires-Python: >=3.7,<3.11
Classifier: Programming Language :: Python :: 3
Classifier: Programming Language :: Python :: 3.7
Classifier: Programming Language :: Python :: 3.8
Classifier: Programming Language :: Python :: 3.9
Classifier: Programming Language :: Python :: 3.10
Requires-Dist: PettingZoo (<1.22.0)
Requires-Dist: SuperSuit
Requires-Dist: cfg_load
Requires-Dist: h5py
Requires-Dist: pqdm
Requires-Dist: pygame
Requires-Dist: pyglet (==1.5.27)
Requires-Dist: rlcard
Requires-Dist: smpl_doc (>=1.1.1)
Requires-Dist: smpl_io
Requires-Dist: tianshou (==0.4.10)
Requires-Dist: torch (==1.13.0)
Requires-Dist: tqdm
